esrf_ontologies/__init__.py
esrf_ontologies/db/ESRFET.json
esrf_ontologies/db/PaNET.json
esrf_ontologies/db/__init__.py
esrf_ontologies/technique/__init__.py
esrf_ontologies/technique/types.py
esrf_ontologies/tests/__init__.py
esrf_ontologies/tests/test_multi_technique_metadata.py
esrf_ontologies/tests/test_single_technique_metadata.py
esrf_ontologies/tests/test_techniques.py
esrf_ontologies-1.2.0.dist-info/licenses/LICENSE.md
esrf_ontologies-1.2.0.dist-info/METADATA
esrf_ontologies-1.2.0.dist-info/WHEEL
esrf_ontologies-1.2.0.dist-info/top_level.txt
esrf_ontologies-1.2.0.dist-info/RECORD
