Metadata-Version: 2.4
Name: esrf-ontologies
Version: 1.2.0
Summary: ESRF Ontologies
Author-email: ESRF <dau-pydev@esrf.fr>
License: # MIT License
Project-URL: Homepage, https://github.com/pan-ontologies/esrf-ontologies/
Project-URL: Documentation, https://esrf-ontologies.readthedocs.io/
Project-URL: Repository, https://github.com/pan-ontologies/esrf-ontologies/
Project-URL: Issues, https://github.com/pan-ontologies/esrf-ontologies/issues
Project-URL: Changelog, https://github.com/pan-ontologies/esrf-ontologies/blob/main/CHANGELOG.md
Classifier: Intended Audience :: Science/Research
Classifier: License :: OSI Approved :: MIT License
Classifier: Programming Language :: Python :: 3
Requires-Python: >=3.8
License-File: LICENSE.md
Requires-Dist: importlib_resources; python_version < "3.9"
Provides-Extra: test
Requires-Dist: pytest>=7; extra == "test"
Provides-Extra: dev
Requires-Dist: esrf-ontologies[test]; extra == "dev"
Requires-Dist: black>=22; extra == "dev"
Requires-Dist: flake8>=4; extra == "dev"
Requires-Dist: owlready2; extra == "dev"
Requires-Dist: isort; extra == "dev"
Provides-Extra: doc
Requires-Dist: esrf-ontologies[test]; extra == "doc"
Requires-Dist: sphinx<9.0.0rc1,>=4.5; extra == "doc"
Requires-Dist: sphinx-autodoc-typehints>=1.16; extra == "doc"
Requires-Dist: pydata-sphinx-theme; extra == "doc"
Requires-Dist: sphinx-copybutton; extra == "doc"
Dynamic: license-file
